LICENSE
README.md
setup.cfg
setup.py
treasury.py
treasurycurves.egg-info/PKG-INFO
treasurycurves.egg-info/SOURCES.txt
treasurycurves.egg-info/dependency_links.txt
treasurycurves.egg-info/entry_points.txt
treasurycurves.egg-info/requires.txt
treasurycurves.egg-info/top_level.txt