Metadata-Version: 2.1
Name: treasurycurves
Version: 1.0.4
Summary: query and analyze US Treasury yield data
Home-page: https://github.com/pepe454/treasury-curves
Author: Danny Fryer
Author-email: 17fryerd@gmail.com
License: MIT
Project-URL: Bug Tracker, https://github.com/pepe454/treasury-curves/issues
Project-URL: Documentation, https://treasury-curves.readthedocs.io/en/latest/
Project-URL: Source Code, https://github.com/pepe454/treasury-curves
Keywords: treasury
Platform: UNKNOWN
Classifier: Programming Language :: Python :: 3.9
Classifier: Topic :: Office/Business :: Financial :: Investment
Classifier: Operating System :: Microsoft
Classifier: Natural Language :: English
Classifier: Development Status :: 4 - Beta
Classifier: License :: Freely Distributable
Classifier: Framework :: Pytest
License-File: LICENSE
